ThaiAddressParser/__init__.py
ThaiAddressParser-1.0.0.dist-info/LICENSE
ThaiAddressParser-1.0.0.dist-info/METADATA
ThaiAddressParser-1.0.0.dist-info/WHEEL
ThaiAddressParser-1.0.0.dist-info/top_level.txt
ThaiAddressParser-1.0.0.dist-info/RECORD
