Metadata-Version: 2.1
Name: ThaiAddressParser
Version: 1.0.0
Summary: Thailand Address Parser
Home-page: https://github.com/HandsomeBrotherShuaiLi/ThaiAddressParser
Author: Shuai Li
Author-email: li.shuai@wustl.edu
License: UNKNOWN
Platform: UNKNOWN
Classifier: Programming Language :: Python :: 3
Classifier: License :: OSI Approved :: MIT License
Classifier: Operating System :: OS Independent
Requires-Dist: bs4
Requires-Dist: requests
Requires-Dist: tqdm
